snmp_rp-0.3.1.dist-info/METADATA
snmp_rp-0.3.1.dist-info/WHEEL
snmp_rp/__init__.py
snmp_rp/snmp_rp.cp39-win_amd64.pyd
snmp_rp-0.3.1.dist-info/RECORD
