Metadata-Version: 2.1
Name: snmp_rp
Version: 0.3.1
Classifier: Programming Language :: Rust
Classifier: Programming Language :: Python :: Implementation :: CPython
Classifier: Programming Language :: Python :: Implementation :: PyPy
Classifier: License :: OSI Approved :: MIT License 
Summary: A SNMP Libray based in Rust SNMP
Keywords: SNMP,Rust,SNMPv2,get,OID
Author: Luka Oliveira
Author-email: pedrolukaoliveira@protonmail.com
Requires-Python: >=3.7
Project-URL: homepage, https://github.com/LukaOliveira/snmp_rp
Project-URL: repository, https://github.com/LukaOliveira/snmp_rp
Project-URL: documentation, https://github.com/LukaOliveira/snmp_rp
